[
  {
    "id": "mast-macs-j0138",
    "title": "MAST: MACS J0138",
    "summary": "HST/JWST assets and lensing meta for MACS J0138.",
    "url": "/datasets/mast-macs-j0138/",
    "source": "MAST",
    "files": []
  },
  {
    "id": "gw-event-set",
    "title": "GW Event Set",
    "summary": "Catalog selection used for GW residual tests.",
    "url": "/datasets/gw-event-set/",
    "source": "LIGO/Virgo/KAGRA",
    "files": []
  },
  {
    "id": "bh-rm-catalog",
    "title": "BH RM Catalog",
    "summary": "Reverberation-mapping anchors used in BH residual analysis.",
    "url": "/datasets/bh-rm-catalog/",
    "source": "RM compilations",
    "files": []
  }
]
